{"datas":[{"name":"【バレンタイン】北条政子","type":2,"rare":5,"era":"鎌倉時代","hp":0,"physical":351,"intelligence":526,"mental":702,"skill":"メンタル・チョコレートⅢ","skillEffect":"味方の心が50%アップ","skillRange":1,"skillStatus":2,"skillSize":1.5,"className":"charactar.ValentineHoujouMasako"},{"name":"聖徳太子","type":2,"rare":5,"era":"飛鳥時代","hp":0,"physical":456,"intelligence":304,"mental":608,"skill":"メンタル・アップⅡ","skillEffect":"自分の心が60%アップ","skillRange":0,"skillStatus":2,"skillSize":1.6,"className":"charactar.SyoutokuTaishi"},{"name":"【バレンタイン】北条政子","type":2,"rare":4,"era":"鎌倉時代","hp":0,"physical":270,"intelligence":405,"mental":540,"skill":"メンタル・チョコレートⅢ","skillEffect":"味方の心が50%アップ","skillRange":1,"skillStatus":2,"skillSize":1.5,"className":"charactar.ValentineHoujouMasako"}]}